{
  "minecraft:recipes/misc/emerald": {
    "criteria": {
      "has_emerald_block": "2024-12-04 20:48:02 +0000"
    },
    "done": true
  },
  "minecraft:recipes/decorations/red_stained_glass_pane": {
    "criteria": {
      "has_glass": "2024-12-04 20:42:26 +0000"
    },
    "done": true
  },
  "minecraft:recipes/decorations/orange_stained_glass_pane": {
    "criteria": {
      "has_glass": "2024-12-04 20:42:23 +0000"
    },
    "done": true
  },
  "minecraft:recipes/decorations/crafting_table": {
    "criteria": {
      "unlock_right_away": "2024-12-04 20:33:55 +0000"
    },
    "done": true
  },
  "minecraft:recipes/decorations/chest": {
    "criteria": {
      "has_lots_of_items": "2024-12-04 20:53:24 +0000"
    },
    "done": true
  },
  "minecraft:adventure/adventuring_time": {
    "criteria": {
      "minecraft:plains": "2024-12-04 20:33:56 +0000"
    },
    "done": false
  },
  "minecraft:recipes/decorations/black_stained_glass_pane": {
    "criteria": {
      "has_glass": "2024-12-04 20:42:25 +0000"
    },
    "done": true
  },
  "minecraft:recipes/decorations/white_stained_glass_pane": {
    "criteria": {
      "has_glass": "2024-12-04 20:41:09 +0000"
    },
    "done": true
  },
  "DataVersion": 3700
}